{"is_source_file": false, "format": "", "description": "", "external_files": [], "external_methods": [], "published": [], "classes": [], "methods": [], "calls": [], "search-terms": [], "state": 2, "file_id": 6, "knowledge_revision": 24, "git_revision": "df72dcefa59b2fe6c000b114c35657556a939ea5", "hash": "ad9ead514ae7783766563c940f3dfe4c", "format-version": 4, "code-base-name": "calculator_frontend", "filename": "README.md", "revision_history": [{"24": "df72dcefa59b2fe6c000b114c35657556a939ea5"}]}